robonav/__init__.py
robonav/program.rbt
robonav/robot.py
robonav/robot.tx
robonav/runner.py
robonav-0.0.4.dist-info/LICENSE
robonav-0.0.4.dist-info/METADATA
robonav-0.0.4.dist-info/WHEEL
robonav-0.0.4.dist-info/entry_points.txt
robonav-0.0.4.dist-info/top_level.txt
robonav-0.0.4.dist-info/RECORD
